dython/__init__.py
dython/_private.py
dython/data_utils.py
dython/model_utils.py
dython/nominal.py
dython/sampling.py
dython/typing.py
dython-0.7.12.dist-info/licenses/LICENSE
dython-0.7.12.dist-info/METADATA
dython-0.7.12.dist-info/WHEEL
dython-0.7.12.dist-info/top_level.txt
dython-0.7.12.dist-info/RECORD
